LICENSE
MANIFEST.in
Makefile
README.rst
setup.py
mys/__init__.py
mys/__main__.py
mys/version.py
mys.egg-info/PKG-INFO
mys.egg-info/SOURCES.txt
mys.egg-info/dependency_links.txt
mys.egg-info/entry_points.txt
mys.egg-info/requires.txt
mys.egg-info/top_level.txt
mys/cli/__init__.py
mys/cli/mys_dir.py
mys/cli/package_config.py
mys/cli/packages_finder.py
mys/cli/run.py
mys/cli/utils.py
mys/cli/subparsers/__init__.py
mys/cli/subparsers/build.py
mys/cli/subparsers/clean.py
mys/cli/subparsers/delete.py
mys/cli/subparsers/dependents.py
mys/cli/subparsers/deps.py
mys/cli/subparsers/doc.py
mys/cli/subparsers/help.py
mys/cli/subparsers/install.py
mys/cli/subparsers/list.py
mys/cli/subparsers/new.py
mys/cli/subparsers/publish.py
mys/cli/subparsers/run.py
mys/cli/subparsers/test.py
mys/cli/subparsers/transpile.py
mys/cli/subparsers/style/__init__.py
mys/cli/subparsers/style/comments_finder.py
mys/cli/subparsers/style/comments_reader.py
mys/cli/subparsers/style/source_styler.py
mys/cli/subparsers/style/utils.py
mys/cli/templates/build/Makefile
mys/cli/templates/doc/conf.py
mys/cli/templates/new/.gitattributes
mys/cli/templates/new/.gitignore
mys/cli/templates/new/LICENSE
mys/cli/templates/new/README.rst
mys/cli/templates/new/package.toml
mys/cli/templates/new/doc/index.rst
mys/cli/templates/new/src/lib.mys
mys/cli/templates/new/src/main.mys
mys/cli/templates/publish/MANIFEST.in
mys/cli/templates/publish/setup.py
mys/coverage/CONTRIBUTORS.txt
mys/coverage/LICENSE.txt
mys/coverage/NOTICE.txt
mys/coverage/README.rst
mys/coverage/__init__.py
mys/coverage/config.py
mys/coverage/control.py
mys/coverage/data.py
mys/coverage/debug.py
mys/coverage/files.py
mys/coverage/html.py
mys/coverage/misc.py
mys/coverage/mys.py
mys/coverage/numbits.py
mys/coverage/phystokens.py
mys/coverage/plugin.py
mys/coverage/report.py
mys/coverage/results.py
mys/coverage/sqldata.py
mys/coverage/templite.py
mys/coverage/version.py
mys/coverage/htmlfiles/coverage_html.js
mys/coverage/htmlfiles/favicon.ico
mys/coverage/htmlfiles/favicon.png
mys/coverage/htmlfiles/index.html
mys/coverage/htmlfiles/jquery.ba-throttle-debounce.min.js
mys/coverage/htmlfiles/jquery.hotkeys.js
