Metadata-Version: 2.1
Name: mys
Version: 0.422.0
Summary: The Mys programming language.
Home-page: https://github.com/eerimoq/mys
Author: Erik Moqvist
Author-email: erik.moqvist@gmail.com
License: MIT
Keywords: programming-language
Classifier: License :: OSI Approved :: MIT License
Classifier: Programming Language :: Python :: 3
Requires-Python: >=3.8
License-File: LICENSE
